music_publisher/__init__.py
music_publisher/admin.py
music_publisher/api.py
music_publisher/apps.py
music_publisher/base.py
music_publisher/cwr_templates.py
music_publisher/data_import.py
music_publisher/forms.py
music_publisher/models.py
music_publisher/royalty_calculation.py
music_publisher/societies.csv
music_publisher/societies.py
music_publisher/urls.py
music_publisher/validators.py
music_publisher/views.py
music_publisher/migrations/0001_initial_squashed_0002_mayday.py
music_publisher/migrations/0003_cwrexport_created_on.py
music_publisher/migrations/0003_cwrexport_created_on_squashed_0008_release_artist.py
music_publisher/migrations/0004_exofile.py
music_publisher/migrations/0005_auto_20220206_1720.py
music_publisher/migrations/0006_alter_cwrexport_nwr_rev.py
music_publisher/migrations/0007_auto_20220724_1028.py
music_publisher/migrations/0008_release_artist.py
music_publisher/migrations/0009_alter_workacknowledgement_society_code_and_more.py
music_publisher/migrations/0010_alter_alternatetitle_options_and_more.py
music_publisher/migrations/0011_alter_alternatetitle_title_type_and_more.py
music_publisher/migrations/__init__.py
music_publisher/templates/raw_cwr.html
music_publisher/templates/admin/add_data_import.html
music_publisher/templates/music_publisher/royalty_calculation.html
music_publisher/templatetags/__init__.py
music_publisher/templatetags/cwr_filters.py
music_publisher/templatetags/cwr_generators.py
music_publisher/templatetags/dmp_dashboard.py
music_publisher/tests/CW220001000_DMP.V21
music_publisher/tests/CW220001052_DMP.V21
music_publisher/tests/__init__.py
music_publisher/tests/dataimport.csv
music_publisher/tests/royaltystatement.csv
music_publisher/tests/royaltystatement_200k_rows.csv
music_publisher/tests/tests.py
django_music_publisher-24.12.1.dist-info/LICENSE
django_music_publisher-24.12.1.dist-info/METADATA
django_music_publisher-24.12.1.dist-info/WHEEL
django_music_publisher-24.12.1.dist-info/top_level.txt
django_music_publisher-24.12.1.dist-info/RECORD
