Metadata-Version: 2.1
Name: django-music-publisher
Version: 24.12.1
Summary: Software for managing music metadata, batch registration of musical works, royalty processing and data exchange.
Home-page: https://django-music-publisher.readthedocs.io/
Author: Matija Kolarić
Author-email: matijakolaric@users.noreply.github.com
License: MIT License
Project-URL: Created by, https://matijakolaric.com
Project-URL: Video Tutorials, https://www.youtube.com/watch?v=Tyk6tYuFBrI&list=PLQ3e-DuNTFt-mwtKvFLK1euk5uCZdhCUP
Project-URL: Documentation, https://django-music-publisher.readthedocs.io/
Project-URL: Code Repository, https://github.com/matijakolaric-com/django-music-publisher/
Classifier: Development Status :: 5 - Production/Stable
Classifier: Environment :: Web Environment
Classifier: Framework :: Django
Classifier: Framework :: Django :: 4.2
Classifier: Intended Audience :: Developers
Classifier: Intended Audience :: Other Audience
Classifier: License :: OSI Approved :: MIT License
Classifier: Operating System :: OS Independent
Classifier: Programming Language :: Python :: 3
Classifier: Programming Language :: Python :: 3 :: Only
Classifier: Programming Language :: Python :: 3.11
Classifier: Programming Language :: Python :: 3.12
Classifier: Programming Language :: Python :: 3.13
License-File: LICENSE
Requires-Dist: Django<5.0,>=4.2.13
Requires-Dist: requests>=2.32.3
